xia_api/__init__.py
xia_api/auth_client.cpython-311-darwin.so
xia_api/message.cpython-311-darwin.so
xia_api/rest.cpython-311-darwin.so
xia_api-0.1.24.dist-info/LICENSE.txt
xia_api-0.1.24.dist-info/METADATA
xia_api-0.1.24.dist-info/WHEEL
xia_api-0.1.24.dist-info/top_level.txt
xia_api-0.1.24.dist-info/RECORD
