Metadata-Version: 2.1
Name: xia-api
Version: 0.1.24
Summary: UNKNOWN
Home-page: https://develop.x-i-a.com/docs/xia-api/0.1.24/index.html
Author: X-I-A
Author-email: admin@x-i-a.com
License: UNKNOWN
Platform: UNKNOWN
Requires-Python: >=3.9
License-File: LICENSE.txt
Requires-Dist: requests
Requires-Dist: xia-fields
Requires-Dist: xia-engine
